Metadata-Version: 1.0
Name: distributionslib
Version: 0.1
Summary: Gaussian and Binomial distributions
Home-page: UNKNOWN
Author: Sanjiv Gupta
Author-email: UNKNOWN
License: UNKNOWN
Platform: UNKNOWN
